fastapi_mock_service/__init__.py
fastapi_mock_service/cli.py
fastapi_mock_service/mock_service.py
fastapi_mock_service/templates/dashboard.html
fastapi_mock_service-1.0.7.dist-info/licenses/LICENSE
fastapi_mock_service-1.0.7.dist-info/METADATA
fastapi_mock_service-1.0.7.dist-info/WHEEL
fastapi_mock_service-1.0.7.dist-info/entry_points.txt
fastapi_mock_service-1.0.7.dist-info/top_level.txt
fastapi_mock_service-1.0.7.dist-info/RECORD
