Metadata-Version: 2.4
Name: fastapi-mock-service
Version: 1.0.7
Summary: Professional mock service library with load testing infrastructure for FastAPI
Home-page: https://gitlab.com/eastden4ik/fastapimockserver
Author: Denis Sviridov
Author-email: Denis Sviridov <Sviridov.DS@bk.ru>
License: MIT
Project-URL: Homepage, https://gitlab.com/eastden4ik/fastapimockserver
Project-URL: Documentation, https://gitlab.com/eastden4ik/fastapimockserver#readme
Project-URL: Repository, https://gitlab.com/eastden4ik/fastapimockserver
Project-URL: Bug Tracker, https://gitlab.com/eastden4ik/fastapimockserver/-/issues
Keywords: fastapi,mock,testing,api,load-testing,prometheus,dashboard
Classifier: Development Status :: 5 - Production/Stable
Classifier: Intended Audience :: Developers
Classifier: License :: OSI Approved :: MIT License
Classifier: Operating System :: OS Independent
Classifier: Programming Language :: Python :: 3
Classifier: Programming Language :: Python :: 3.8
Classifier: Programming Language :: Python :: 3.9
Classifier: Programming Language :: Python :: 3.10
Classifier: Programming Language :: Python :: 3.11
Classifier: Programming Language :: Python :: 3.12
Classifier: Framework :: FastAPI
Classifier: Topic :: Software Development :: Libraries :: Python Modules
Classifier: Topic :: Software Development :: Testing :: Mocking
Classifier: Topic :: Internet :: WWW/HTTP :: HTTP Servers
Requires-Python: >=3.8
License-File: LICENSE
Requires-Dist: fastapi>=0.104.1
Requires-Dist: uvicorn[standard]>=0.24.0
Requires-Dist: starlette>=0.27.0
Requires-Dist: tortoise-orm>=0.20.0
Requires-Dist: aiosqlite>=0.19.0
Requires-Dist: prometheus-client>=0.17.0
Requires-Dist: httpx>=0.25.0
Requires-Dist: jinja2>=3.1.0
Requires-Dist: pydantic>=2.4.0
Requires-Dist: importlib-resources>=6.0.0; python_version < "3.9"
Provides-Extra: dev
Requires-Dist: pytest>=6.0.0; extra == "dev"
Requires-Dist: pytest-asyncio>=0.21.0; extra == "dev"
Requires-Dist: black>=22.0.0; extra == "dev"
Requires-Dist: flake8>=4.0.0; extra == "dev"
Requires-Dist: mypy>=0.900; extra == "dev"
Dynamic: author
Dynamic: home-page
Dynamic: license-file
Dynamic: requires-python
